CHANGES.rst
COPYING
MANIFEST.in
README.rst
pyjslint.py
setup.py
pyjslint.egg-info/PKG-INFO
pyjslint.egg-info/SOURCES.txt
pyjslint.egg-info/dependency_links.txt
pyjslint.egg-info/entry_points.txt
pyjslint.egg-info/not-zip-safe
pyjslint.egg-info/top_level.txt