Metadata-Version: 1.0
Name: pyjslint
Version: 0.3.1
Summary: JSLint wrapper
Home-page: https://github.com/Yaco-Sistemas/pyjslint/
Author: Alejandro Blanco
Author-email: ablanco@yaco.es
License: BSD-3
Keywords: jslint javascript lint hook qa
Platform: UNKNOWN
Classifier: Development Status :: 4 - Beta
Classifier: Environment :: Console
Classifier: Intended Audience :: Developers
Classifier: Intended Audience :: System Administrators
Classifier: License :: OSI Approved :: BSD License
Classifier: Natural Language :: English
Classifier: Programming Language :: JavaScript
Classifier: Programming Language :: Python
Classifier: Topic :: Software Development :: Quality Assurance
